xpansiv_xsignals/Authenticator.py
xpansiv_xsignals/DatalakeHandler.py
xpansiv_xsignals/ExceptionHandler.py
xpansiv_xsignals/HTTPCalller.py
xpansiv_xsignals/StatusHandler.py
xpansiv_xsignals/TaskHandler.py
xpansiv_xsignals/Timeseries.py
xpansiv_xsignals/__init__.py
xpansiv_xsignals/constants.py
xpansiv_xsignals-1.0.1.dist-info/LICENSE
xpansiv_xsignals-1.0.1.dist-info/METADATA
xpansiv_xsignals-1.0.1.dist-info/WHEEL
xpansiv_xsignals-1.0.1.dist-info/top_level.txt
xpansiv_xsignals-1.0.1.dist-info/RECORD
