Metadata-Version: 2.1
Name: xpansiv_xsignals
Version: 1.0.1
Summary: Python SDK for the XPANSIV XSIGNALS platform
Home-page: https://xpansiv.com/
Author: Xpansiv
Author-email: info@xpansiv.com
Classifier: Programming Language :: Python :: 3
Classifier: License :: OSI Approved :: MIT License
Classifier: Operating System :: OS Independent
Requires-Python: >=3.6
License-File: LICENSE
Requires-Dist: requests>=2.27.1
Requires-Dist: urllib3>=1.26.9
Requires-Dist: auth0-python>=4.7.0
